DIYables_Pico_Joystick/DIYables_Pico_Joystick.py
DIYables_Pico_Joystick/__init__.py
DIYables_Pico_Joystick-0.1.0.dist-info/LICENSE
DIYables_Pico_Joystick-0.1.0.dist-info/METADATA
DIYables_Pico_Joystick-0.1.0.dist-info/WHEEL
DIYables_Pico_Joystick-0.1.0.dist-info/top_level.txt
DIYables_Pico_Joystick-0.1.0.dist-info/RECORD
